LICENSE
MANIFEST.in
README.md
setup.py
django_send_messages.egg-info/PKG-INFO
django_send_messages.egg-info/SOURCES.txt
django_send_messages.egg-info/dependency_links.txt
django_send_messages.egg-info/not-zip-safe
django_send_messages.egg-info/top_level.txt
sms/__init__.py
sms/admin.py
sms/message.py
sms/models.py
sms/signals.py
sms/tests.py
sms/urls.py
sms/views.py
sms/backends/__init__.py
sms/backends/base.py
sms/backends/locmem.py
sms/backends/yunpian.py
sms/backends/yunpian_util.py
sms/conf/__init__.py
sms/conf/settings.py
sms/migrations/__init__.py
testproj/__init__.py
testproj/settings.py
testproj/urls.py
testproj/wsgi.py