Metadata-Version: 1.1
Name: django-send-messages
Version: 1.0.0
Summary: A simple API to send messages, includes Yunpian backend and Wechat(weixin) backend.
Home-page: https://github.com/hwbuluo/django-send-messages
Author: Leon Liu
Author-email: liuyong@hwbuluo.com
License: BSD
Platform: UNKNOWN
Classifier: Development Status :: 3 - Alpha
Classifier: Programming Language :: Python
Classifier: Programming Language :: Python :: 2
Classifier: Framework :: Django
Classifier: Intended Audience :: Developers
Classifier: License :: OSI Approved :: BSD License
Classifier: Operating System :: OS Independent
Classifier: Topic :: Internet :: WWW/HTTP
